{
  "maintenance_agency_id" : "ECB",
  "cube_id" : "BIRD_CRDT_FCLTY_RSK_DT_ELDM_1",
  "name" : "Credit facility risk data",
  "code" : "BIRD_CRDT_FCLTY_RSK_DT_ELDM",
  "framework_id" : "BIRD",
  "cube_structure_id" : "BIRD_CRDT_FCLTY_RSK_DT_ELDM_1",
  "cube_type" : "ELDM",
  "is_allowed" : null,
  "valid_from" : "2023-07-01",
  "valid_to" : "9999-12-31",
  "version" : "1",
  "description" : "Credit facility risk data is risk related information about a Credit facility.",
  "published" : "true",
  "dataset_url" : null,
  "filters" : null,
  "di_export" : null,
  "cube_to_combination" : [ ],
  "cube_to_table" : [ ]
}