{
  "maintenance_agency_id" : "ECB",
  "cube_relationship_id" : "BIRD_INSTRMNT_ENTTY_RL_ASSGNMNT_EIL__BIRD_ENTTY_RL_EIL__DT_RFRNC_1",
  "code" : "BIRD_INSTRMNT_ENTTY_RL_ASSGNMNT_EIL_1__BIRD_ENTTY_RL_EIL_1__DT_RFRNC",
  "name" : "Entity role has many Instrument Entity role assignment",
  "description" : null,
  "type_of_relationship" : "ASS",
  "valid_from" : "2023-07-01",
  "valid_to" : "9999-12-31",
  "version" : "1",
  "primary_cube_id" : "BIRD_ENTTY_RL_EIL_1",
  "primary_cube_variable_code" : "DT_RFRNC",
  "foreign_cube_id" : "BIRD_INSTRMNT_ENTTY_RL_ASSGNMNT_EIL_1",
  "foreign_cube_variable_code" : "DT_RFRNC",
  "primary_cube_cardinality" : "1",
  "foreign_cube_cardinality" : "N",
  "primary_cube_mandatoriness" : "true",
  "foreign_cube_mandatoriness" : "true"
}