{
  "maintenance_agency_id" : "ECB",
  "subdomain_id" : "BLNC_SHT_RCGNSD_EXCHNG_TRDBL_DRVTV_LBLTY_PSTN_TYP",
  "name" : "Balance sheet recognised exchange tradable derivative liability position type",
  "domain_id" : "EXCHNG_TRDBL_DRVTV_PSTN_RL_TYP",
  "is_listed" : "true",
  "code" : "BLNC_SHT_RCGNSD_EXCHNG_TRDBL_DRVTV_LBLTY_PSTN_TYP",
  "facet_id" : null,
  "description" : "Balance sheet recognised exchange tradable derivative liability position type",
  "is_natural" : "false",
  "subdomain_enumeration" : [ {
    "member_id" : "EXCHNG_TRDBL_DRVTV_PSTN_RL_TYP_7",
    "subdomain_id" : "BLNC_SHT_RCGNSD_EXCHNG_TRDBL_DRVTV_LBLTY_PSTN_TYP",
    "valid_from" : "2023-01-01",
    "valid_to" : "9999-12-31",
    "order" : "0"
  }, {
    "member_id" : "EXCHNG_TRDBL_DRVTV_PSTN_RL_TYP_8",
    "subdomain_id" : "BLNC_SHT_RCGNSD_EXCHNG_TRDBL_DRVTV_LBLTY_PSTN_TYP",
    "valid_from" : "2023-01-01",
    "valid_to" : "9999-12-31",
    "order" : "0"
  } ]
}