{
  "maintenance_agency_id" : "ECB",
  "subdomain_id" : "LGL_PRCDNG_STTS",
  "name" : "Legal proceeding status",
  "domain_id" : "LGL_PRCDNG_STTS",
  "is_listed" : "true",
  "code" : "LGL_PRCDNG_STTS",
  "facet_id" : null,
  "description" : "Legal proceeding status",
  "is_natural" : "false",
  "subdomain_enumeration" : [ {
    "member_id" : "LGL_PRCDNG_STTS_1",
    "subdomain_id" : "LGL_PRCDNG_STTS",
    "valid_from" : "2022-03-01",
    "valid_to" : "9999-12-31",
    "order" : "0"
  }, {
    "member_id" : "LGL_PRCDNG_STTS_2",
    "subdomain_id" : "LGL_PRCDNG_STTS",
    "valid_from" : "2022-03-01",
    "valid_to" : "9999-12-31",
    "order" : "0"
  }, {
    "member_id" : "LGL_PRCDNG_STTS_3",
    "subdomain_id" : "LGL_PRCDNG_STTS",
    "valid_from" : "2022-03-01",
    "valid_to" : "9999-12-31",
    "order" : "0"
  }, {
    "member_id" : "LGL_PRCDNG_STTS_4",
    "subdomain_id" : "LGL_PRCDNG_STTS",
    "valid_from" : "2022-03-01",
    "valid_to" : "9999-12-31",
    "order" : "0"
  } ]
}