{
  "maintenance_agency_id" : "ECB2",
  "member_id" : "ECB2_InSeTy_ECB2_149",
  "code" : "149",
  "name" : "Unguaranteed _Senior_Security level - No detailed information available",
  "domain_id" : "ECB2_InSeTy",
  "description" : "In case of unguaranteed securities, there are no obligations to guarantors to make payments to the holder of the security if the issuer fails to meet the obligation to make repayments arising under the instrument secured by the guarantor. Senior securities are required to be repaid before subordinated securities. To be reported, in case the security level (secured/usecured) is not available / applicable."
}