{
  "maintenance_agency_id" : "EBA",
  "cube_id" : "EBA_FINREP_EBA_F_20.04_FINREP_2017-A",
  "name" : "Geographical breakdown of assets by residence of the counterparty",
  "code" : "F_20.04",
  "framework_id" : "EBA_FINREP",
  "cube_structure_id" : "EBA_FINREP_EBA_F_20.04_FINREP_2017-A",
  "cube_type" : "D",
  "is_allowed" : null,
  "valid_from" : "2018-03-31",
  "valid_to" : "2018-12-30",
  "version" : "FINREP 2017-A",
  "description" : "Geographical breakdown of assets by residence of the counterparty",
  "published" : "true",
  "dataset_url" : null,
  "filters" : null,
  "di_export" : null,
  "cube_to_combination" : [ {
    "cube_id" : "EBA_FINREP_EBA_F_20.04_FINREP_2017-A",
    "combination_id" : "EBA_67802"
  }, {
    "cube_id" : "EBA_FINREP_EBA_F_20.04_FINREP_2017-A",
    "combination_id" : "EBA_150845"
  }, {
    "cube_id" : "EBA_FINREP_EBA_F_20.04_FINREP_2017-A",
    "combination_id" : "EBA_150846"
  }, {
    "cube_id" : "EBA_FINREP_EBA_F_20.04_FINREP_2017-A",
    "combination_id" : "EBA_150898"
  }, {
    "cube_id" : "EBA_FINREP_EBA_F_20.04_FINREP_2017-A",
    "combination_id" : "EBA_150899"
  }, {
    "cube_id" : "EBA_FINREP_EBA_F_20.04_FINREP_2017-A",
    "combination_id" : "EBA_150900"
  }, {
    "cube_id" : "EBA_FINREP_EBA_F_20.04_FINREP_2017-A",
    "combination_id" : "EBA_150930"
  }, {
    "cube_id" : "EBA_FINREP_EBA_F_20.04_FINREP_2017-A",
    "combination_id" : "EBA_150931"
  }, {
    "cube_id" : "EBA_FINREP_EBA_F_20.04_FINREP_2017-A",
    "combination_id" : "EBA_150932"
  }, {
    "cube_id" : "EBA_FINREP_EBA_F_20.04_FINREP_2017-A",
    "combination_id" : "EBA_150933"
  }, {
    "cube_id" : "EBA_FINREP_EBA_F_20.04_FINREP_2017-A",
    "combination_id" : "EBA_150934"
  }, {
    "cube_id" : "EBA_FINREP_EBA_F_20.04_FINREP_2017-A",
    "combination_id" : "EBA_150935"
  }, {
    "cube_id" : "EBA_FINREP_EBA_F_20.04_FINREP_2017-A",
    "combination_id" : "EBA_150936"
  }, {
    "cube_id" : "EBA_FINREP_EBA_F_20.04_FINREP_2017-A",
    "combination_id" : "EBA_150937"
  }, {
    "cube_id" : "EBA_FINREP_EBA_F_20.04_FINREP_2017-A",
    "combination_id" : "EBA_150938"
  }, {
    "cube_id" : "EBA_FINREP_EBA_F_20.04_FINREP_2017-A",
    "combination_id" : "EBA_150939"
  }, {
    "cube_id" : "EBA_FINREP_EBA_F_20.04_FINREP_2017-A",
    "combination_id" : "EBA_150940"
  }, {
    "cube_id" : "EBA_FINREP_EBA_F_20.04_FINREP_2017-A",
    "combination_id" : "EBA_150941"
  }, {
    "cube_id" : "EBA_FINREP_EBA_F_20.04_FINREP_2017-A",
    "combination_id" : "EBA_150942"
  }, {
    "cube_id" : "EBA_FINREP_EBA_F_20.04_FINREP_2017-A",
    "combination_id" : "EBA_150943"
  }, {
    "cube_id" : "EBA_FINREP_EBA_F_20.04_FINREP_2017-A",
    "combination_id" : "EBA_150944"
  }, {
    "cube_id" : "EBA_FINREP_EBA_F_20.04_FINREP_2017-A",
    "combination_id" : "EBA_150984"
  }, {
    "cube_id" : "EBA_FINREP_EBA_F_20.04_FINREP_2017-A",
    "combination_id" : "EBA_150985"
  }, {
    "cube_id" : "EBA_FINREP_EBA_F_20.04_FINREP_2017-A",
    "combination_id" : "EBA_150986"
  }, {
    "cube_id" : "EBA_FINREP_EBA_F_20.04_FINREP_2017-A",
    "combination_id" : "EBA_150847"
  }, {
    "cube_id" : "EBA_FINREP_EBA_F_20.04_FINREP_2017-A",
    "combination_id" : "EBA_150848"
  }, {
    "cube_id" : "EBA_FINREP_EBA_F_20.04_FINREP_2017-A",
    "combination_id" : "EBA_150849"
  }, {
    "cube_id" : "EBA_FINREP_EBA_F_20.04_FINREP_2017-A",
    "combination_id" : "EBA_150850"
  }, {
    "cube_id" : "EBA_FINREP_EBA_F_20.04_FINREP_2017-A",
    "combination_id" : "EBA_150851"
  }, {
    "cube_id" : "EBA_FINREP_EBA_F_20.04_FINREP_2017-A",
    "combination_id" : "EBA_150852"
  }, {
    "cube_id" : "EBA_FINREP_EBA_F_20.04_FINREP_2017-A",
    "combination_id" : "EBA_150853"
  }, {
    "cube_id" : "EBA_FINREP_EBA_F_20.04_FINREP_2017-A",
    "combination_id" : "EBA_150854"
  }, {
    "cube_id" : "EBA_FINREP_EBA_F_20.04_FINREP_2017-A",
    "combination_id" : "EBA_150855"
  }, {
    "cube_id" : "EBA_FINREP_EBA_F_20.04_FINREP_2017-A",
    "combination_id" : "EBA_150856"
  }, {
    "cube_id" : "EBA_FINREP_EBA_F_20.04_FINREP_2017-A",
    "combination_id" : "EBA_150896"
  }, {
    "cube_id" : "EBA_FINREP_EBA_F_20.04_FINREP_2017-A",
    "combination_id" : "EBA_150897"
  }, {
    "cube_id" : "EBA_FINREP_EBA_F_20.04_FINREP_2017-A",
    "combination_id" : "EBA_112790"
  }, {
    "cube_id" : "EBA_FINREP_EBA_F_20.04_FINREP_2017-A",
    "combination_id" : "EBA_112792"
  }, {
    "cube_id" : "EBA_FINREP_EBA_F_20.04_FINREP_2017-A",
    "combination_id" : "EBA_112793"
  }, {
    "cube_id" : "EBA_FINREP_EBA_F_20.04_FINREP_2017-A",
    "combination_id" : "EBA_112797"
  }, {
    "cube_id" : "EBA_FINREP_EBA_F_20.04_FINREP_2017-A",
    "combination_id" : "EBA_112798"
  }, {
    "cube_id" : "EBA_FINREP_EBA_F_20.04_FINREP_2017-A",
    "combination_id" : "EBA_112799"
  }, {
    "cube_id" : "EBA_FINREP_EBA_F_20.04_FINREP_2017-A",
    "combination_id" : "EBA_152491"
  }, {
    "cube_id" : "EBA_FINREP_EBA_F_20.04_FINREP_2017-A",
    "combination_id" : "EBA_152492"
  }, {
    "cube_id" : "EBA_FINREP_EBA_F_20.04_FINREP_2017-A",
    "combination_id" : "EBA_152493"
  }, {
    "cube_id" : "EBA_FINREP_EBA_F_20.04_FINREP_2017-A",
    "combination_id" : "EBA_152494"
  }, {
    "cube_id" : "EBA_FINREP_EBA_F_20.04_FINREP_2017-A",
    "combination_id" : "EBA_152495"
  }, {
    "cube_id" : "EBA_FINREP_EBA_F_20.04_FINREP_2017-A",
    "combination_id" : "EBA_152496"
  }, {
    "cube_id" : "EBA_FINREP_EBA_F_20.04_FINREP_2017-A",
    "combination_id" : "EBA_152497"
  }, {
    "cube_id" : "EBA_FINREP_EBA_F_20.04_FINREP_2017-A",
    "combination_id" : "EBA_152576"
  }, {
    "cube_id" : "EBA_FINREP_EBA_F_20.04_FINREP_2017-A",
    "combination_id" : "EBA_152578"
  }, {
    "cube_id" : "EBA_FINREP_EBA_F_20.04_FINREP_2017-A",
    "combination_id" : "EBA_152579"
  }, {
    "cube_id" : "EBA_FINREP_EBA_F_20.04_FINREP_2017-A",
    "combination_id" : "EBA_152580"
  }, {
    "cube_id" : "EBA_FINREP_EBA_F_20.04_FINREP_2017-A",
    "combination_id" : "EBA_152581"
  }, {
    "cube_id" : "EBA_FINREP_EBA_F_20.04_FINREP_2017-A",
    "combination_id" : "EBA_152582"
  }, {
    "cube_id" : "EBA_FINREP_EBA_F_20.04_FINREP_2017-A",
    "combination_id" : "EBA_152583"
  }, {
    "cube_id" : "EBA_FINREP_EBA_F_20.04_FINREP_2017-A",
    "combination_id" : "EBA_152594"
  }, {
    "cube_id" : "EBA_FINREP_EBA_F_20.04_FINREP_2017-A",
    "combination_id" : "EBA_152599"
  }, {
    "cube_id" : "EBA_FINREP_EBA_F_20.04_FINREP_2017-A",
    "combination_id" : "EBA_112757"
  }, {
    "cube_id" : "EBA_FINREP_EBA_F_20.04_FINREP_2017-A",
    "combination_id" : "EBA_112759"
  }, {
    "cube_id" : "EBA_FINREP_EBA_F_20.04_FINREP_2017-A",
    "combination_id" : "EBA_112763"
  }, {
    "cube_id" : "EBA_FINREP_EBA_F_20.04_FINREP_2017-A",
    "combination_id" : "EBA_112764"
  }, {
    "cube_id" : "EBA_FINREP_EBA_F_20.04_FINREP_2017-A",
    "combination_id" : "EBA_112765"
  }, {
    "cube_id" : "EBA_FINREP_EBA_F_20.04_FINREP_2017-A",
    "combination_id" : "EBA_112767"
  }, {
    "cube_id" : "EBA_FINREP_EBA_F_20.04_FINREP_2017-A",
    "combination_id" : "EBA_112771"
  }, {
    "cube_id" : "EBA_FINREP_EBA_F_20.04_FINREP_2017-A",
    "combination_id" : "EBA_112773"
  }, {
    "cube_id" : "EBA_FINREP_EBA_F_20.04_FINREP_2017-A",
    "combination_id" : "EBA_112781"
  }, {
    "cube_id" : "EBA_FINREP_EBA_F_20.04_FINREP_2017-A",
    "combination_id" : "EBA_112782"
  }, {
    "cube_id" : "EBA_FINREP_EBA_F_20.04_FINREP_2017-A",
    "combination_id" : "EBA_112785"
  }, {
    "cube_id" : "EBA_FINREP_EBA_F_20.04_FINREP_2017-A",
    "combination_id" : "EBA_112801"
  }, {
    "cube_id" : "EBA_FINREP_EBA_F_20.04_FINREP_2017-A",
    "combination_id" : "EBA_112805"
  }, {
    "cube_id" : "EBA_FINREP_EBA_F_20.04_FINREP_2017-A",
    "combination_id" : "EBA_112806"
  }, {
    "cube_id" : "EBA_FINREP_EBA_F_20.04_FINREP_2017-A",
    "combination_id" : "EBA_112807"
  }, {
    "cube_id" : "EBA_FINREP_EBA_F_20.04_FINREP_2017-A",
    "combination_id" : "EBA_112809"
  }, {
    "cube_id" : "EBA_FINREP_EBA_F_20.04_FINREP_2017-A",
    "combination_id" : "EBA_152363"
  }, {
    "cube_id" : "EBA_FINREP_EBA_F_20.04_FINREP_2017-A",
    "combination_id" : "EBA_152364"
  }, {
    "cube_id" : "EBA_FINREP_EBA_F_20.04_FINREP_2017-A",
    "combination_id" : "EBA_152365"
  }, {
    "cube_id" : "EBA_FINREP_EBA_F_20.04_FINREP_2017-A",
    "combination_id" : "EBA_152366"
  }, {
    "cube_id" : "EBA_FINREP_EBA_F_20.04_FINREP_2017-A",
    "combination_id" : "EBA_152367"
  }, {
    "cube_id" : "EBA_FINREP_EBA_F_20.04_FINREP_2017-A",
    "combination_id" : "EBA_152368"
  }, {
    "cube_id" : "EBA_FINREP_EBA_F_20.04_FINREP_2017-A",
    "combination_id" : "EBA_152408"
  }, {
    "cube_id" : "EBA_FINREP_EBA_F_20.04_FINREP_2017-A",
    "combination_id" : "EBA_152409"
  }, {
    "cube_id" : "EBA_FINREP_EBA_F_20.04_FINREP_2017-A",
    "combination_id" : "EBA_152410"
  }, {
    "cube_id" : "EBA_FINREP_EBA_F_20.04_FINREP_2017-A",
    "combination_id" : "EBA_152411"
  }, {
    "cube_id" : "EBA_FINREP_EBA_F_20.04_FINREP_2017-A",
    "combination_id" : "EBA_152412"
  }, {
    "cube_id" : "EBA_FINREP_EBA_F_20.04_FINREP_2017-A",
    "combination_id" : "EBA_152473"
  }, {
    "cube_id" : "EBA_FINREP_EBA_F_20.04_FINREP_2017-A",
    "combination_id" : "EBA_152474"
  }, {
    "cube_id" : "EBA_FINREP_EBA_F_20.04_FINREP_2017-A",
    "combination_id" : "EBA_152475"
  }, {
    "cube_id" : "EBA_FINREP_EBA_F_20.04_FINREP_2017-A",
    "combination_id" : "EBA_152476"
  }, {
    "cube_id" : "EBA_FINREP_EBA_F_20.04_FINREP_2017-A",
    "combination_id" : "EBA_152477"
  }, {
    "cube_id" : "EBA_FINREP_EBA_F_20.04_FINREP_2017-A",
    "combination_id" : "EBA_152478"
  }, {
    "cube_id" : "EBA_FINREP_EBA_F_20.04_FINREP_2017-A",
    "combination_id" : "EBA_152479"
  }, {
    "cube_id" : "EBA_FINREP_EBA_F_20.04_FINREP_2017-A",
    "combination_id" : "EBA_152480"
  }, {
    "cube_id" : "EBA_FINREP_EBA_F_20.04_FINREP_2017-A",
    "combination_id" : "EBA_152481"
  }, {
    "cube_id" : "EBA_FINREP_EBA_F_20.04_FINREP_2017-A",
    "combination_id" : "EBA_152482"
  }, {
    "cube_id" : "EBA_FINREP_EBA_F_20.04_FINREP_2017-A",
    "combination_id" : "EBA_152483"
  }, {
    "cube_id" : "EBA_FINREP_EBA_F_20.04_FINREP_2017-A",
    "combination_id" : "EBA_152484"
  }, {
    "cube_id" : "EBA_FINREP_EBA_F_20.04_FINREP_2017-A",
    "combination_id" : "EBA_152362"
  }, {
    "cube_id" : "EBA_FINREP_EBA_F_20.04_FINREP_2017-A",
    "combination_id" : "EBA_152485"
  }, {
    "cube_id" : "EBA_FINREP_EBA_F_20.04_FINREP_2017-A",
    "combination_id" : "EBA_152486"
  }, {
    "cube_id" : "EBA_FINREP_EBA_F_20.04_FINREP_2017-A",
    "combination_id" : "EBA_152487"
  }, {
    "cube_id" : "EBA_FINREP_EBA_F_20.04_FINREP_2017-A",
    "combination_id" : "EBA_152488"
  }, {
    "cube_id" : "EBA_FINREP_EBA_F_20.04_FINREP_2017-A",
    "combination_id" : "EBA_152489"
  }, {
    "cube_id" : "EBA_FINREP_EBA_F_20.04_FINREP_2017-A",
    "combination_id" : "EBA_152490"
  }, {
    "cube_id" : "EBA_FINREP_EBA_F_20.04_FINREP_2017-A",
    "combination_id" : "EBA_150992"
  }, {
    "cube_id" : "EBA_FINREP_EBA_F_20.04_FINREP_2017-A",
    "combination_id" : "EBA_151049"
  }, {
    "cube_id" : "EBA_FINREP_EBA_F_20.04_FINREP_2017-A",
    "combination_id" : "EBA_151050"
  }, {
    "cube_id" : "EBA_FINREP_EBA_F_20.04_FINREP_2017-A",
    "combination_id" : "EBA_151051"
  }, {
    "cube_id" : "EBA_FINREP_EBA_F_20.04_FINREP_2017-A",
    "combination_id" : "EBA_151052"
  }, {
    "cube_id" : "EBA_FINREP_EBA_F_20.04_FINREP_2017-A",
    "combination_id" : "EBA_151053"
  }, {
    "cube_id" : "EBA_FINREP_EBA_F_20.04_FINREP_2017-A",
    "combination_id" : "EBA_151054"
  }, {
    "cube_id" : "EBA_FINREP_EBA_F_20.04_FINREP_2017-A",
    "combination_id" : "EBA_151055"
  }, {
    "cube_id" : "EBA_FINREP_EBA_F_20.04_FINREP_2017-A",
    "combination_id" : "EBA_151056"
  }, {
    "cube_id" : "EBA_FINREP_EBA_F_20.04_FINREP_2017-A",
    "combination_id" : "EBA_151057"
  }, {
    "cube_id" : "EBA_FINREP_EBA_F_20.04_FINREP_2017-A",
    "combination_id" : "EBA_151058"
  }, {
    "cube_id" : "EBA_FINREP_EBA_F_20.04_FINREP_2017-A",
    "combination_id" : "EBA_151059"
  }, {
    "cube_id" : "EBA_FINREP_EBA_F_20.04_FINREP_2017-A",
    "combination_id" : "EBA_151060"
  }, {
    "cube_id" : "EBA_FINREP_EBA_F_20.04_FINREP_2017-A",
    "combination_id" : "EBA_151061"
  }, {
    "cube_id" : "EBA_FINREP_EBA_F_20.04_FINREP_2017-A",
    "combination_id" : "EBA_151062"
  }, {
    "cube_id" : "EBA_FINREP_EBA_F_20.04_FINREP_2017-A",
    "combination_id" : "EBA_151063"
  }, {
    "cube_id" : "EBA_FINREP_EBA_F_20.04_FINREP_2017-A",
    "combination_id" : "EBA_151064"
  }, {
    "cube_id" : "EBA_FINREP_EBA_F_20.04_FINREP_2017-A",
    "combination_id" : "EBA_151065"
  }, {
    "cube_id" : "EBA_FINREP_EBA_F_20.04_FINREP_2017-A",
    "combination_id" : "EBA_151066"
  }, {
    "cube_id" : "EBA_FINREP_EBA_F_20.04_FINREP_2017-A",
    "combination_id" : "EBA_151067"
  }, {
    "cube_id" : "EBA_FINREP_EBA_F_20.04_FINREP_2017-A",
    "combination_id" : "EBA_151068"
  }, {
    "cube_id" : "EBA_FINREP_EBA_F_20.04_FINREP_2017-A",
    "combination_id" : "EBA_151069"
  }, {
    "cube_id" : "EBA_FINREP_EBA_F_20.04_FINREP_2017-A",
    "combination_id" : "EBA_151070"
  }, {
    "cube_id" : "EBA_FINREP_EBA_F_20.04_FINREP_2017-A",
    "combination_id" : "EBA_151071"
  }, {
    "cube_id" : "EBA_FINREP_EBA_F_20.04_FINREP_2017-A",
    "combination_id" : "EBA_151072"
  }, {
    "cube_id" : "EBA_FINREP_EBA_F_20.04_FINREP_2017-A",
    "combination_id" : "EBA_152159"
  }, {
    "cube_id" : "EBA_FINREP_EBA_F_20.04_FINREP_2017-A",
    "combination_id" : "EBA_152357"
  }, {
    "cube_id" : "EBA_FINREP_EBA_F_20.04_FINREP_2017-A",
    "combination_id" : "EBA_152358"
  }, {
    "cube_id" : "EBA_FINREP_EBA_F_20.04_FINREP_2017-A",
    "combination_id" : "EBA_150987"
  }, {
    "cube_id" : "EBA_FINREP_EBA_F_20.04_FINREP_2017-A",
    "combination_id" : "EBA_150988"
  }, {
    "cube_id" : "EBA_FINREP_EBA_F_20.04_FINREP_2017-A",
    "combination_id" : "EBA_150989"
  }, {
    "cube_id" : "EBA_FINREP_EBA_F_20.04_FINREP_2017-A",
    "combination_id" : "EBA_150990"
  }, {
    "cube_id" : "EBA_FINREP_EBA_F_20.04_FINREP_2017-A",
    "combination_id" : "EBA_150991"
  }, {
    "cube_id" : "EBA_FINREP_EBA_F_20.04_FINREP_2017-A",
    "combination_id" : "EBA_152359"
  }, {
    "cube_id" : "EBA_FINREP_EBA_F_20.04_FINREP_2017-A",
    "combination_id" : "EBA_152360"
  }, {
    "cube_id" : "EBA_FINREP_EBA_F_20.04_FINREP_2017-A",
    "combination_id" : "EBA_152361"
  } ],
  "cube_to_table" : [ {
    "cube_id" : "EBA_FINREP_EBA_F_20.04_FINREP_2017-A",
    "table_id" : "EBA_FINREP_EBA_F_20.04_FINREP_2017-A"
  } ]
}